ä¸Šå›è®²åˆ°ï¼Œä¸ºäº†è®©æ‰€æœ‰çš„åŠ¨ç‰©éƒ½èƒ½å‚åŠ èµ›é©¬ï¼ŒJava 7å¼•å…¥äº†invokedynamicæœºåˆ¶ï¼Œå…è®¸è°ƒç”¨ä»»æ„ç±»çš„â€œèµ›è·‘â€æ–¹æ³•ã€‚ä¸è¿‡ï¼Œæˆ‘ä»¬å¹¶æ²¡æœ‰è®²è§£invokedynamicï¼Œè€Œæ˜¯æ·±å…¥åœ°æ¢è®¨äº†å®ƒæ‰€ä¾èµ–çš„æ–¹æ³•å¥æŸ„ã€‚

ä»Šå¤©ï¼Œæˆ‘ä¾¿æ¥æ­£å¼åœ°ä»‹ç»invokedynamicæŒ‡ä»¤ï¼Œè®²è®²å®ƒæ˜¯å¦‚ä½•ç”Ÿæˆè°ƒç”¨ç‚¹ï¼Œå¹¶ä¸”å…è®¸åº”ç”¨ç¨‹åºè‡ªå·±å†³å®šé“¾æ¥è‡³å“ªä¸€ä¸ªæ–¹æ³•ä¸­çš„ã€‚

## invokedynamicæŒ‡ä»¤

invokedynamicæ˜¯Java 7å¼•å…¥çš„ä¸€æ¡æ–°æŒ‡ä»¤ï¼Œç”¨ä»¥æ”¯æŒåŠ¨æ€è¯­è¨€çš„æ–¹æ³•è°ƒç”¨ã€‚å…·ä½“æ¥è¯´ï¼Œå®ƒå°†è°ƒç”¨ç‚¹ï¼ˆCallSiteï¼‰æŠ½è±¡æˆä¸€ä¸ªJavaç±»ï¼Œå¹¶ä¸”å°†åŸæœ¬ç”±Javaè™šæ‹Ÿæœºæ§åˆ¶çš„æ–¹æ³•è°ƒç”¨ä»¥åŠæ–¹æ³•é“¾æ¥æš´éœ²ç»™äº†åº”ç”¨ç¨‹åºã€‚åœ¨è¿è¡Œè¿‡ç¨‹ä¸­ï¼Œæ¯ä¸€æ¡invokedynamicæŒ‡ä»¤å°†æ†ç»‘ä¸€ä¸ªè°ƒç”¨ç‚¹ï¼Œå¹¶ä¸”ä¼šè°ƒç”¨è¯¥è°ƒç”¨ç‚¹æ‰€é“¾æ¥çš„æ–¹æ³•å¥æŸ„ã€‚

åœ¨ç¬¬ä¸€æ¬¡æ‰§è¡ŒinvokedynamicæŒ‡ä»¤æ—¶ï¼ŒJavaè™šæ‹Ÿæœºä¼šè°ƒç”¨è¯¥æŒ‡ä»¤æ‰€å¯¹åº”çš„å¯åŠ¨æ–¹æ³•ï¼ˆBootStrap Methodï¼‰ï¼Œæ¥ç”Ÿæˆå‰é¢æåˆ°çš„è°ƒç”¨ç‚¹ï¼Œå¹¶ä¸”å°†ä¹‹ç»‘å®šè‡³è¯¥invokedynamicæŒ‡ä»¤ä¸­ã€‚åœ¨ä¹‹åçš„è¿è¡Œè¿‡ç¨‹ä¸­ï¼ŒJavaè™šæ‹Ÿæœºåˆ™ä¼šç›´æ¥è°ƒç”¨ç»‘å®šçš„è°ƒç”¨ç‚¹æ‰€é“¾æ¥çš„æ–¹æ³•å¥æŸ„ã€‚

åœ¨å­—èŠ‚ç ä¸­ï¼Œå¯åŠ¨æ–¹æ³•æ˜¯ç”¨æ–¹æ³•å¥æŸ„æ¥æŒ‡å®šçš„ã€‚è¿™ä¸ªæ–¹æ³•å¥æŸ„æŒ‡å‘ä¸€ä¸ªè¿”å›ç±»å‹ä¸ºè°ƒç”¨ç‚¹çš„é™æ€æ–¹æ³•ã€‚è¯¥æ–¹æ³•å¿…é¡»æ¥æ”¶ä¸‰ä¸ªå›ºå®šçš„å‚æ•°ï¼Œåˆ†åˆ«ä¸ºä¸€ä¸ªLookupç±»å®ä¾‹ï¼Œä¸€ä¸ªç”¨æ¥æŒ‡ä»£ç›®æ ‡æ–¹æ³•åå­—çš„å­—ç¬¦ä¸²ï¼Œä»¥åŠè¯¥è°ƒç”¨ç‚¹èƒ½å¤Ÿé“¾æ¥çš„æ–¹æ³•å¥æŸ„çš„ç±»å‹ã€‚

é™¤äº†è¿™ä¸‰ä¸ªå¿…éœ€å‚æ•°ä¹‹å¤–ï¼Œå¯åŠ¨æ–¹æ³•è¿˜å¯ä»¥æ¥æ”¶è‹¥å¹²ä¸ªå…¶ä»–çš„å‚æ•°ï¼Œç”¨æ¥è¾…åŠ©ç”Ÿæˆè°ƒç”¨ç‚¹ï¼Œæˆ–è€…å®šä½æ‰€è¦é“¾æ¥çš„ç›®æ ‡æ–¹æ³•ã€‚

```
import java.lang.invoke.*;

class Horse {
  public void race() {
    System.out.println("Horse.race()"); 
  }
}

class Deer {
  public void race() {
    System.out.println("Deer.race()");
  }
}

// javac Circuit.java
// java Circuit
public class Circuit {

  public static void startRace(Object obj) {
    // aload obj
    // invokedynamic race()
  }

  public static void main(String[] args) {
    startRace(new Horse());
    // startRace(new Deer());
  }
  
  public static CallSite bootstrap(MethodHandles.Lookup l, String name, MethodType callSiteType) throws Throwable {
    MethodHandle mh = l.findVirtual(Horse.class, name, MethodType.methodType(void.class));
    return new ConstantCallSite(mh.asType(callSiteType));
  }
}
```

æˆ‘åœ¨æ–‡ç¨¿ä¸­è´´äº†ä¸€æ®µä»£ç ï¼Œå…¶ä¸­ä¾¿åŒ…å«ä¸€ä¸ªå¯åŠ¨æ–¹æ³•ã€‚å®ƒå°†æ¥æ”¶å‰é¢æåˆ°çš„ä¸‰ä¸ªå›ºå®šå‚æ•°ï¼Œå¹¶ä¸”è¿”å›ä¸€ä¸ªé“¾æ¥è‡³Horse.raceæ–¹æ³•çš„ConstantCallSiteã€‚

è¿™é‡Œçš„ConstantCallSiteæ˜¯ä¸€ç§ä¸å¯ä»¥æ›´æ”¹é“¾æ¥å¯¹è±¡çš„è°ƒç”¨ç‚¹ã€‚é™¤æ­¤ä¹‹å¤–ï¼ŒJavaæ ¸å¿ƒç±»åº“è¿˜æä¾›å¤šç§å¯ä»¥æ›´æ”¹é“¾æ¥å¯¹è±¡çš„è°ƒç”¨ç‚¹ï¼Œæ¯”å¦‚MutableCallSiteå’ŒVolatileCallSiteã€‚

è¿™ä¸¤è€…çš„åŒºåˆ«å°±å¥½æ¯”æ­£å¸¸å­—æ®µå’Œvolatileå­—æ®µä¹‹é—´çš„åŒºåˆ«ã€‚æ­¤å¤–ï¼Œåº”ç”¨ç¨‹åºè¿˜å¯ä»¥è‡ªå®šä¹‰è°ƒç”¨ç‚¹ç±»ï¼Œæ¥æ»¡è¶³ç‰¹å®šçš„é‡é“¾æ¥éœ€æ±‚ã€‚

ç”±äºJavaæš‚ä¸æ”¯æŒç›´æ¥ç”ŸæˆinvokedynamicæŒ‡ä»¤\[1]ï¼Œæ‰€ä»¥æ¥ä¸‹æ¥æˆ‘ä¼šå€ŸåŠ©ä¹‹å‰ä»‹ç»è¿‡çš„å­—èŠ‚ç å·¥å…·ASMæ¥å®ç°è¿™ä¸€ç›®çš„ã€‚

```
import java.io.IOException;
import java.lang.invoke.*;
import java.nio.file.*;

import org.objectweb.asm.*;

// javac -cp /path/to/asm-all-6.0_BETA.jar:. ASMHelper.java
// java -cp /path/to/asm-all-6.0_BETA.jar:. ASMHelper
// java Circuit
public class ASMHelper implements Opcodes {

  private static class MyMethodVisitor extends MethodVisitor {

    private static final String BOOTSTRAP_CLASS_NAME = Circuit.class.getName().replace('.', '/');
    private static final String BOOTSTRAP_METHOD_NAME = "bootstrap";
    private static final String BOOTSTRAP_METHOD_DESC = MethodType
        .methodType(CallSite.class, MethodHandles.Lookup.class, String.class, MethodType.class)
        .toMethodDescriptorString();

    private static final String TARGET_METHOD_NAME = "race";
    private static final String TARGET_METHOD_DESC = "(Ljava/lang/Object;)V";

    public final MethodVisitor mv;

    public MyMethodVisitor(int api, MethodVisitor mv) {
      super(api);
      this.mv = mv;
    }

    @Override
    public void visitCode() {
      mv.visitCode();
      mv.visitVarInsn(ALOAD, 0);
      Handle h = new Handle(H_INVOKESTATIC, BOOTSTRAP_CLASS_NAME, BOOTSTRAP_METHOD_NAME, BOOTSTRAP_METHOD_DESC, false);
      mv.visitInvokeDynamicInsn(TARGET_METHOD_NAME, TARGET_METHOD_DESC, h);
      mv.visitInsn(RETURN);
      mv.visitMaxs(1, 1);
      mv.visitEnd();
    }
  }

  public static void main(String[] args) throws IOException {
    ClassReader cr = new ClassReader("Circuit");
    ClassWriter cw = new ClassWriter(cr, ClassWriter.COMPUTE_FRAMES);
    ClassVisitor cv = new ClassVisitor(ASM6, cw) {
      @Override
      public MethodVisitor visitMethod(int access, String name, String descriptor, String signature,
          String[] exceptions) {
        MethodVisitor visitor = super.visitMethod(access, name, descriptor, signature, exceptions);
        if ("startRace".equals(name)) {
          return new MyMethodVisitor(ASM6, visitor);
        }
        return visitor;
      }
    };
    cr.accept(cv, ClassReader.SKIP_FRAMES);

    Files.write(Paths.get("Circuit.class"), cw.toByteArray());
  }
}
```

ä½ æ— éœ€ç†è§£ä¸Šé¢è¿™æ®µä»£ç çš„å…·ä½“å«ä¹‰ï¼Œåªé¡»äº†è§£å®ƒä¼šæ›´æ”¹åŒä¸€ç›®å½•ä¸‹Circuitç±»çš„startRace(Object)æ–¹æ³•ï¼Œä½¿ä¹‹åŒ…å«invokedynamicæŒ‡ä»¤ï¼Œæ‰§è¡Œæ‰€è°“çš„èµ›è·‘æ–¹æ³•ã€‚

```
 public static void startRace(java.lang.Object);
         0: aload_0
         1: invokedynamic #80,  0 // race:(Ljava/lang/Object;)V
         6: return
```

å¦‚æœä½ è¶³å¤Ÿç»†å¿ƒçš„è¯ï¼Œä½ ä¼šå‘ç°è¯¥æŒ‡ä»¤æ‰€è°ƒç”¨çš„èµ›è·‘æ–¹æ³•çš„æè¿°ç¬¦ï¼Œå’ŒHorse.raceæ–¹æ³•æˆ–è€…Deer.raceæ–¹æ³•çš„æè¿°ç¬¦å¹¶ä¸ä¸€è‡´ã€‚è¿™æ˜¯å› ä¸ºinvokedynamicæŒ‡ä»¤æœ€ç»ˆè°ƒç”¨çš„æ˜¯æ–¹æ³•å¥æŸ„ï¼Œè€Œæ–¹æ³•å¥æŸ„ä¼šå°†è°ƒç”¨è€…å½“æˆç¬¬ä¸€ä¸ªå‚æ•°ã€‚å› æ­¤ï¼Œåˆšåˆšæåˆ°çš„é‚£ä¸¤ä¸ªæ–¹æ³•æ°æ°ç¬¦åˆè¿™ä¸ªæè¿°ç¬¦æ‰€å¯¹åº”çš„æ–¹æ³•å¥æŸ„ç±»å‹ã€‚

åˆ°ç›®å‰ä¸ºæ­¢ï¼Œæˆ‘ä»¬å·²ç»å¯ä»¥é€šè¿‡invokedynamicè°ƒç”¨Horse.raceæ–¹æ³•äº†ã€‚ä¸ºäº†æ”¯æŒè°ƒç”¨ä»»æ„ç±»çš„raceæ–¹æ³•ï¼Œæˆ‘å®ç°äº†ä¸€ä¸ªç®€å•çš„å•æ€å†…è”ç¼“å­˜ã€‚å¦‚æœè°ƒç”¨è€…çš„ç±»å‹å‘½ä¸­ç¼“å­˜ä¸­çš„ç±»å‹ï¼Œä¾¿ç›´æ¥è°ƒç”¨ç¼“å­˜ä¸­çš„æ–¹æ³•å¥æŸ„ï¼Œå¦åˆ™ä¾¿æ›´æ–°ç¼“å­˜ã€‚

```
// éœ€è¦æ›´æ”¹ASMHelper.MyMethodVisitorä¸­çš„BOOTSTRAP_CLASS_NAME
import java.lang.invoke.*;

public class MonomorphicInlineCache {

  private final MethodHandles.Lookup lookup;
  private final String name;

  public MonomorphicInlineCache(MethodHandles.Lookup lookup, String name) {
    this.lookup = lookup;
    this.name = name;
  }

  private Class<?> cachedClass = null;
  private MethodHandle mh = null;

  public void invoke(Object receiver) throws Throwable {
    if (cachedClass != receiver.getClass()) {
      cachedClass = receiver.getClass();
      mh = lookup.findVirtual(cachedClass, name, MethodType.methodType(void.class));
    }
    mh.invoke(receiver);
  }

  public static CallSite bootstrap(MethodHandles.Lookup l, String name, MethodType callSiteType) throws Throwable {
    MonomorphicInlineCache ic = new MonomorphicInlineCache(l, name);
    MethodHandle mh = l.findVirtual(MonomorphicInlineCache.class, "invoke", MethodType.methodType(void.class, Object.class));
    return new ConstantCallSite(mh.bindTo(ic));
  }
}
```

å¯ä»¥çœ‹åˆ°ï¼Œå°½ç®¡invokedynamicæŒ‡ä»¤è°ƒç”¨çš„æ˜¯æ‰€è°“çš„raceæ–¹æ³•ï¼Œä½†æ˜¯å®é™…ä¸Šæˆ‘è¿”å›äº†ä¸€ä¸ªé“¾æ¥è‡³åä¸ºâ€œinvokeâ€çš„æ–¹æ³•çš„è°ƒç”¨ç‚¹ã€‚ç”±äºè°ƒç”¨ç‚¹ä»…è¦æ±‚æ–¹æ³•å¥æŸ„çš„ç±»å‹èƒ½å¤ŸåŒ¹é…ï¼Œå› æ­¤è¿™ä¸ªé“¾æ¥æ˜¯åˆæ³•çš„ã€‚

ä¸è¿‡ï¼Œè¿™æ­£æ˜¯invokedynamicçš„ç›®çš„ï¼Œä¹Ÿå°±æ˜¯å°†è°ƒç”¨ç‚¹ä¸ç›®æ ‡æ–¹æ³•çš„é“¾æ¥äº¤ç”±åº”ç”¨ç¨‹åºæ¥åšï¼Œå¹¶ä¸”ä¾èµ–äºåº”ç”¨ç¨‹åºå¯¹ç›®æ ‡æ–¹æ³•è¿›è¡ŒéªŒè¯ã€‚æ‰€ä»¥ï¼Œå¦‚æœåº”ç”¨ç¨‹åºå°†èµ›è·‘æ–¹æ³•é“¾æ¥è‡³å…”å­çš„ç¡è§‰æ–¹æ³•ï¼Œé‚£ä¹Ÿåªèƒ½æ€ªåº”ç”¨ç¨‹åºè‡ªå·±äº†ã€‚

## Java 8çš„Lambdaè¡¨è¾¾å¼

åœ¨Java 8ä¸­ï¼ŒLambdaè¡¨è¾¾å¼ä¹Ÿæ˜¯å€ŸåŠ©invokedynamicæ¥å®ç°çš„ã€‚

å…·ä½“æ¥è¯´ï¼ŒJavaç¼–è¯‘å™¨åˆ©ç”¨invokedynamicæŒ‡ä»¤æ¥ç”Ÿæˆå®ç°äº†å‡½æ•°å¼æ¥å£çš„é€‚é…å™¨ã€‚è¿™é‡Œçš„å‡½æ•°å¼æ¥å£æŒ‡çš„æ˜¯ä»…åŒ…æ‹¬ä¸€ä¸ªédefaultæ¥å£æ–¹æ³•çš„æ¥å£ï¼Œä¸€èˆ¬é€šè¿‡@FunctionalInterfaceæ³¨è§£ã€‚ä¸è¿‡å°±ç®—æ˜¯æ²¡æœ‰ä½¿ç”¨è¯¥æ³¨è§£ï¼ŒJavaç¼–è¯‘å™¨ä¹Ÿä¼šå°†ç¬¦åˆæ¡ä»¶çš„æ¥å£è¾¨è®¤ä¸ºå‡½æ•°å¼æ¥å£ã€‚

```
int x = ..
IntStream.of(1, 2, 3).map(i -> i * 2).map(i -> i * x);
```

ä¸¾ä¸ªä¾‹å­ï¼Œä¸Šé¢è¿™æ®µä»£ç ä¼šå¯¹IntStreamä¸­çš„å…ƒç´ è¿›è¡Œä¸¤æ¬¡æ˜ å°„ã€‚æˆ‘ä»¬çŸ¥é“ï¼Œæ˜ å°„æ–¹æ³•mapæ‰€æ¥æ”¶çš„å‚æ•°æ˜¯IntUnaryOperatorï¼ˆè¿™æ˜¯ä¸€ä¸ªå‡½æ•°å¼æ¥å£ï¼‰ã€‚ä¹Ÿå°±æ˜¯è¯´ï¼Œåœ¨è¿è¡Œè¿‡ç¨‹ä¸­æˆ‘ä»¬éœ€è¦å°†i-&gt;i*2å’Œi-&gt;i*x è¿™ä¸¤ä¸ªLambdaè¡¨è¾¾å¼è½¬åŒ–æˆIntUnaryOperatorçš„å®ä¾‹ã€‚è¿™ä¸ªè½¬åŒ–è¿‡ç¨‹ä¾¿æ˜¯ç”±invokedynamicæ¥å®ç°çš„ã€‚

åœ¨ç¼–è¯‘è¿‡ç¨‹ä¸­ï¼ŒJavaç¼–è¯‘å™¨ä¼šå¯¹Lambdaè¡¨è¾¾å¼è¿›è¡Œè§£è¯­æ³•ç³–ï¼ˆdesugarï¼‰ï¼Œç”Ÿæˆä¸€ä¸ªæ–¹æ³•æ¥ä¿å­˜Lambdaè¡¨è¾¾å¼çš„å†…å®¹ã€‚è¯¥æ–¹æ³•çš„å‚æ•°åˆ—è¡¨ä¸ä»…åŒ…å«åŸæœ¬Lambdaè¡¨è¾¾å¼çš„å‚æ•°ï¼Œè¿˜åŒ…å«å®ƒæ‰€æ•è·çš„å˜é‡ã€‚(æ³¨ï¼šæ–¹æ³•å¼•ç”¨ï¼Œå¦‚Horse::raceï¼Œåˆ™ä¸ä¼šç”Ÿæˆç”Ÿæˆé¢å¤–çš„æ–¹æ³•ã€‚)

åœ¨ä¸Šé¢é‚£ä¸ªä¾‹å­ä¸­ï¼Œç¬¬ä¸€ä¸ªLambdaè¡¨è¾¾å¼æ²¡æœ‰æ•è·å…¶ä»–å˜é‡ï¼Œè€Œç¬¬äºŒä¸ªLambdaè¡¨è¾¾å¼ï¼ˆä¹Ÿå°±æ˜¯i-&gt;i\*xï¼‰åˆ™ä¼šæ•è·å±€éƒ¨å˜é‡xã€‚è¿™ä¸¤ä¸ªLambdaè¡¨è¾¾å¼å¯¹åº”çš„æ–¹æ³•å¦‚ä¸‹æ‰€ç¤ºã€‚å¯ä»¥çœ‹åˆ°ï¼Œæ‰€æ•è·çš„å˜é‡åŒæ ·ä¹Ÿä¼šä½œä¸ºå‚æ•°ä¼ å…¥ç”Ÿæˆçš„æ–¹æ³•ä¹‹ä¸­ã€‚

```
  // i -> i * 2
  private static int lambda$0(int);
    Code:
       0: iload_0
       1: iconst_2
       2: imul
       3: ireturn

  // i -> i * x
  private static int lambda$1(int, int);
    Code:
       0: iload_1
       1: iload_0
       2: imul
       3: ireturn
```

ç¬¬ä¸€æ¬¡æ‰§è¡ŒinvokedynamicæŒ‡ä»¤æ—¶ï¼Œå®ƒæ‰€å¯¹åº”çš„å¯åŠ¨æ–¹æ³•ä¼šé€šè¿‡ASMæ¥ç”Ÿæˆä¸€ä¸ªé€‚é…å™¨ç±»ã€‚è¿™ä¸ªé€‚é…å™¨ç±»å®ç°äº†å¯¹åº”çš„å‡½æ•°å¼æ¥å£ï¼Œåœ¨æˆ‘ä»¬çš„ä¾‹å­ä¸­ï¼Œä¹Ÿå°±æ˜¯IntUnaryOperatorã€‚å¯åŠ¨æ–¹æ³•çš„è¿”å›å€¼æ˜¯ä¸€ä¸ªConstantCallSiteï¼Œå…¶é“¾æ¥å¯¹è±¡ä¸ºä¸€ä¸ªè¿”å›é€‚é…å™¨ç±»å®ä¾‹çš„æ–¹æ³•å¥æŸ„ã€‚

æ ¹æ®Lambdaè¡¨è¾¾å¼æ˜¯å¦æ•è·å…¶ä»–å˜é‡ï¼Œå¯åŠ¨æ–¹æ³•ç”Ÿæˆçš„é€‚é…å™¨ç±»ä»¥åŠæ‰€é“¾æ¥çš„æ–¹æ³•å¥æŸ„çš†ä¸åŒã€‚

å¦‚æœè¯¥Lambdaè¡¨è¾¾å¼æ²¡æœ‰æ•è·å…¶ä»–å˜é‡ï¼Œé‚£ä¹ˆå¯ä»¥è®¤ä¸ºå®ƒæ˜¯ä¸Šä¸‹æ–‡æ— å…³çš„ã€‚å› æ­¤ï¼Œå¯åŠ¨æ–¹æ³•å°†æ–°å»ºä¸€ä¸ªé€‚é…å™¨ç±»çš„å®ä¾‹ï¼Œå¹¶ä¸”ç”Ÿæˆä¸€ä¸ªç‰¹æ®Šçš„æ–¹æ³•å¥æŸ„ï¼Œå§‹ç»ˆè¿”å›è¯¥å®ä¾‹ã€‚

å¦‚æœè¯¥Lambdaè¡¨è¾¾å¼æ•è·äº†å…¶ä»–å˜é‡ï¼Œé‚£ä¹ˆæ¯æ¬¡æ‰§è¡Œè¯¥invokedynamicæŒ‡ä»¤ï¼Œæˆ‘ä»¬éƒ½è¦æ›´æ–°è¿™äº›æ•è·äº†çš„å˜é‡ï¼Œä»¥é˜²æ­¢å®ƒä»¬å‘ç”Ÿäº†å˜åŒ–ã€‚

å¦å¤–ï¼Œä¸ºäº†ä¿è¯Lambdaè¡¨è¾¾å¼çš„çº¿ç¨‹å®‰å…¨ï¼Œæˆ‘ä»¬æ— æ³•å…±äº«åŒä¸€ä¸ªé€‚é…å™¨ç±»çš„å®ä¾‹ã€‚å› æ­¤ï¼Œåœ¨æ¯æ¬¡æ‰§è¡ŒinvokedynamicæŒ‡ä»¤æ—¶ï¼Œæ‰€è°ƒç”¨çš„æ–¹æ³•å¥æŸ„éƒ½éœ€è¦æ–°å»ºä¸€ä¸ªé€‚é…å™¨ç±»å®ä¾‹ã€‚

åœ¨è¿™ç§æƒ…å†µä¸‹ï¼Œå¯åŠ¨æ–¹æ³•ç”Ÿæˆçš„é€‚é…å™¨ç±»å°†åŒ…å«ä¸€ä¸ªé¢å¤–çš„é™æ€æ–¹æ³•ï¼Œæ¥æ„é€ é€‚é…å™¨ç±»çš„å®ä¾‹ã€‚è¯¥æ–¹æ³•å°†æ¥æ”¶è¿™äº›æ•è·çš„å‚æ•°ï¼Œå¹¶ä¸”å°†å®ƒä»¬ä¿å­˜ä¸ºé€‚é…å™¨ç±»å®ä¾‹çš„å®ä¾‹å­—æ®µã€‚

ä½ å¯ä»¥é€šè¿‡è™šæ‹Ÿæœºå‚æ•°-Djdk.internal.lambda.dumpProxyClasses=/DUMP/PATHå¯¼å‡ºè¿™äº›å…·ä½“çš„é€‚é…å™¨ç±»ã€‚è¿™é‡Œæˆ‘å¯¼å‡ºäº†ä¸Šé¢è¿™ä¸ªä¾‹å­ä¸­ä¸¤ä¸ªLambdaè¡¨è¾¾å¼å¯¹åº”çš„é€‚é…å™¨ç±»ã€‚

```
// i->i*2 å¯¹åº”çš„é€‚é…å™¨ç±»
final class LambdaTest$$Lambda$1 implements IntUnaryOperator {
 private LambdaTest$$Lambda$1();
  Code:
    0: aload_0
    1: invokespecial java/lang/Object."<init>":()V
    4: return

 public int applyAsInt(int);
  Code:
    0: iload_1
    1: invokestatic LambdaTest.lambda$0:(I)I
    4: ireturn
}

// i->i*x å¯¹åº”çš„é€‚é…å™¨ç±»
final class LambdaTest$$Lambda$2 implements IntUnaryOperator {
 private final int arg$1;

 private LambdaTest$$Lambda$2(int);
  Code:
    0: aload_0
    1: invokespecial java/lang/Object."<init>":()V
    4: aload_0
    5: iload_1
    6: putfield arg$1:I
    9: return

 private static java.util.function.IntUnaryOperator get$Lambda(int);
  Code:
    0: new LambdaTest$$Lambda$2
    3: dup
    4: iload_0
    5: invokespecial "<init>":(I)V
    8: areturn

 public int applyAsInt(int);
  Code:
    0: aload_0
    1: getfield arg$1:I
    4: iload_1
    5: invokestatic LambdaTest.lambda$1:(II)I
    8: ireturn
}
```

å¯ä»¥çœ‹åˆ°ï¼Œæ•è·äº†å±€éƒ¨å˜é‡çš„Lambdaè¡¨è¾¾å¼å¤šå‡ºäº†ä¸€ä¸ªget$Lambdaçš„æ–¹æ³•ã€‚å¯åŠ¨æ–¹æ³•ä¾¿ä¼šæ‰€è¿”å›çš„è°ƒç”¨ç‚¹é“¾æ¥è‡³æŒ‡å‘è¯¥æ–¹æ³•çš„æ–¹æ³•å¥æŸ„ã€‚ä¹Ÿå°±æ˜¯è¯´ï¼Œæ¯æ¬¡æ‰§è¡ŒinvokedynamicæŒ‡ä»¤æ—¶ï¼Œéƒ½ä¼šè°ƒç”¨è‡³è¿™ä¸ªæ–¹æ³•ä¸­ï¼Œå¹¶æ„é€ ä¸€ä¸ªæ–°çš„é€‚é…å™¨ç±»å®ä¾‹ã€‚

è¿™ä¸ªå¤šå‡ºæ¥çš„æ–°å»ºå®ä¾‹ä¼šå¯¹ç¨‹åºæ€§èƒ½é€ æˆå½±å“å—ï¼Ÿ

## Lambdaä»¥åŠæ–¹æ³•å¥æŸ„çš„æ€§èƒ½åˆ†æ

æˆ‘å†æ¬¡è¯·å‡ºæµ‹è¯•åå°„è°ƒç”¨æ€§èƒ½å¼€é”€çš„é‚£æ®µä»£ç ï¼Œå¹¶å°†å…¶æ”¹é€ æˆä½¿ç”¨Lambdaè¡¨è¾¾å¼çš„v6ç‰ˆæœ¬ã€‚

```
// v6ç‰ˆæœ¬
import java.util.function.IntConsumer;

public class Test {
  public static void target(int i) { }

  public static void main(String[] args) throws Exception {
    long current = System.currentTimeMillis();
    for (int i = 1; i <= 2_000_000_000; i++) {
      if (i % 100_000_000 == 0) {
        long temp = System.currentTimeMillis();
        System.out.println(temp - current);
        current = temp;
      }

      ((IntConsumer) j -> Test.target(j)).accept(128);
      // ((IntConsumer) Test::target.accept(128);
    }
  }
}
```

æµ‹é‡ç»“æœæ˜¾ç¤ºï¼Œå®ƒä¸ç›´æ¥è°ƒç”¨çš„æ€§èƒ½å¹¶æ— å¤ªå¤§çš„åŒºåˆ«ã€‚ä¹Ÿå°±æ˜¯è¯´ï¼Œå³æ—¶ç¼–è¯‘å™¨èƒ½å¤Ÿå°†è½¬æ¢Lambdaè¡¨è¾¾å¼æ‰€ä½¿ç”¨çš„invokedynamicï¼Œä»¥åŠå¯¹IntConsumer.acceptæ–¹æ³•çš„è°ƒç”¨ç»Ÿç»Ÿå†…è”è¿›æ¥ï¼Œæœ€ç»ˆä¼˜åŒ–ä¸ºç©ºæ“ä½œã€‚

è¿™ä¸ªå…¶å®ä¸éš¾ç†è§£ï¼šLambdaè¡¨è¾¾å¼æ‰€ä½¿ç”¨çš„invokedynamicå°†ç»‘å®šä¸€ä¸ªConstantCallSiteï¼Œå…¶é“¾æ¥çš„ç›®æ ‡æ–¹æ³•æ— æ³•æ”¹å˜ã€‚å› æ­¤ï¼Œå³æ—¶ç¼–è¯‘å™¨ä¼šå°†è¯¥ç›®æ ‡æ–¹æ³•ç›´æ¥å†…è”è¿›æ¥ã€‚å¯¹äºè¿™ç±»æ²¡æœ‰æ•è·å˜é‡çš„Lambdaè¡¨è¾¾å¼è€Œè¨€ï¼Œç›®æ ‡æ–¹æ³•åªå®Œæˆäº†ä¸€ä¸ªåŠ¨ä½œï¼Œä¾¿æ˜¯åŠ è½½ç¼“å­˜çš„é€‚é…å™¨ç±»å¸¸é‡ã€‚

å¦ä¸€æ–¹é¢ï¼Œå¯¹IntConsumer.acceptæ–¹æ³•çš„è°ƒç”¨å®åˆ™æ˜¯å¯¹é€‚é…å™¨ç±»çš„acceptæ–¹æ³•çš„è°ƒç”¨ã€‚

å¦‚æœä½ æŸ¥çœ‹äº†acceptæ–¹æ³•å¯¹åº”çš„å­—èŠ‚ç çš„è¯ï¼Œä½ ä¼šå‘ç°å®ƒä»…åŒ…å«ä¸€ä¸ªæ–¹æ³•è°ƒç”¨ï¼Œè°ƒç”¨è‡³Javaç¼–è¯‘å™¨åœ¨è§£Lambdaè¯­æ³•ç³–æ—¶ç”Ÿæˆçš„æ–¹æ³•ã€‚

è¯¥æ–¹æ³•çš„å†…å®¹ä¾¿æ˜¯Lambdaè¡¨è¾¾å¼çš„å†…å®¹ï¼Œä¹Ÿå°±æ˜¯ç›´æ¥è°ƒç”¨ç›®æ ‡æ–¹æ³•Test.targetã€‚å°†è¿™å‡ ä¸ªæ–¹æ³•è°ƒç”¨å†…è”è¿›æ¥ä¹‹åï¼ŒåŸæœ¬å¯¹acceptæ–¹æ³•çš„è°ƒç”¨åˆ™ä¼šè¢«ä¼˜åŒ–ä¸ºç©ºæ“ä½œã€‚

ä¸‹é¢æˆ‘å°†ä¹‹å‰çš„ä»£ç æ›´æ”¹ä¸ºå¸¦æ•è·å˜é‡çš„v7ç‰ˆæœ¬ã€‚ç†è®ºä¸Šï¼Œæ¯æ¬¡è°ƒç”¨invokedynamicæŒ‡ä»¤ï¼ŒJavaè™šæ‹Ÿæœºéƒ½ä¼šæ–°å»ºä¸€ä¸ªé€‚é…å™¨ç±»çš„å®ä¾‹ã€‚ç„¶è€Œï¼Œå®é™…è¿è¡Œç»“æœè¿˜æ˜¯ä¸ç›´æ¥è°ƒç”¨çš„æ€§èƒ½ä¸€è‡´ã€‚

```
// v7ç‰ˆæœ¬
import java.util.function.IntConsumer;

public class Test {
  public static void target(int i) { }

  public static void main(String[] args) throws Exception {
    int x = 2;

    long current = System.currentTimeMillis();
    for (int i = 1; i <= 2_000_000_000; i++) {
      if (i % 100_000_000 == 0) {
        long temp = System.currentTimeMillis();
        System.out.println(temp - current);
        current = temp;
      }

      ((IntConsumer) j -> Test.target(x + j)).accept(128);
    }
  }
}
```

æ˜¾ç„¶ï¼Œå³æ—¶ç¼–è¯‘å™¨çš„é€ƒé€¸åˆ†æåˆå°†è¯¥æ–°å»ºå®ä¾‹ç»™ä¼˜åŒ–æ‰äº†ã€‚æˆ‘ä»¬å¯ä»¥é€šè¿‡è™šæ‹Ÿæœºå‚æ•°-XX:-DoEscapeAnalysisæ¥å…³é—­é€ƒé€¸åˆ†æã€‚æœç„¶ï¼Œè¿™æ—¶å€™æµ‹å¾—çš„å€¼çº¦ä¸ºç›´æ¥è°ƒç”¨çš„2.5å€ã€‚

å°½ç®¡é€ƒé€¸åˆ†æèƒ½å¤Ÿå»é™¤è¿™äº›é¢å¤–çš„æ–°å»ºå®ä¾‹å¼€é”€ï¼Œä½†æ˜¯å®ƒä¹Ÿä¸æ˜¯æ—¶æ—¶å¥æ•ˆã€‚å®ƒéœ€è¦åŒæ—¶æ»¡è¶³ä¸¤ä»¶äº‹ï¼šinvokedynamicæŒ‡ä»¤æ‰€æ‰§è¡Œçš„æ–¹æ³•å¥æŸ„èƒ½å¤Ÿå†…è”ï¼Œå’Œæ¥ä¸‹æ¥çš„å¯¹acceptæ–¹æ³•çš„è°ƒç”¨ä¹Ÿèƒ½å†…è”ã€‚

åªæœ‰è¿™æ ·ï¼Œé€ƒé€¸åˆ†ææ‰èƒ½åˆ¤å®šè¯¥é€‚é…å™¨å®ä¾‹ä¸é€ƒé€¸ã€‚å¦åˆ™ï¼Œæˆ‘ä»¬ä¼šåœ¨è¿è¡Œè¿‡ç¨‹ä¸­ä¸åœåœ°ç”Ÿæˆé€‚é…å™¨ç±»å®ä¾‹ã€‚æ‰€ä»¥ï¼Œæˆ‘ä»¬åº”å½“å°½é‡ä½¿ç”¨éæ•è·çš„Lambdaè¡¨è¾¾å¼ã€‚

## æ€»ç»“ä¸å®è·µ

ä»Šå¤©æˆ‘ä»‹ç»äº†invokedynamicæŒ‡ä»¤ä»¥åŠLambdaè¡¨è¾¾å¼çš„å®ç°ã€‚

invokedymaicæŒ‡ä»¤æŠ½è±¡å‡ºè°ƒç”¨ç‚¹çš„æ¦‚å¿µï¼Œå¹¶ä¸”å°†è°ƒç”¨è¯¥è°ƒç”¨ç‚¹æ‰€é“¾æ¥çš„æ–¹æ³•å¥æŸ„ã€‚åœ¨ç¬¬ä¸€æ¬¡æ‰§è¡ŒinvokedynamicæŒ‡ä»¤æ—¶ï¼ŒJavaè™šæ‹Ÿæœºå°†æ‰§è¡Œå®ƒæ‰€å¯¹åº”çš„å¯åŠ¨æ–¹æ³•ï¼Œç”Ÿæˆå¹¶ä¸”ç»‘å®šä¸€ä¸ªè°ƒç”¨ç‚¹ã€‚ä¹‹åå¦‚æœå†æ¬¡æ‰§è¡Œè¯¥æŒ‡ä»¤ï¼ŒJavaè™šæ‹Ÿæœºåˆ™ç›´æ¥è°ƒç”¨å·²ç»ç»‘å®šäº†çš„è°ƒç”¨ç‚¹æ‰€é“¾æ¥çš„æ–¹æ³•ã€‚

Lambdaè¡¨è¾¾å¼åˆ°å‡½æ•°å¼æ¥å£çš„è½¬æ¢æ˜¯é€šè¿‡invokedynamicæŒ‡ä»¤æ¥å®ç°çš„ã€‚è¯¥invokedynamicæŒ‡ä»¤å¯¹åº”çš„å¯åŠ¨æ–¹æ³•å°†é€šè¿‡ASMç”Ÿæˆä¸€ä¸ªé€‚é…å™¨ç±»ã€‚

å¯¹äºæ²¡æœ‰æ•è·å…¶ä»–å˜é‡çš„Lambdaè¡¨è¾¾å¼ï¼Œè¯¥invokedynamicæŒ‡ä»¤å§‹ç»ˆè¿”å›åŒä¸€ä¸ªé€‚é…å™¨ç±»çš„å®ä¾‹ã€‚å¯¹äºæ•è·äº†å…¶ä»–å˜é‡çš„Lambdaè¡¨è¾¾å¼ï¼Œæ¯æ¬¡æ‰§è¡ŒinvokedynamicæŒ‡ä»¤å°†æ–°å»ºä¸€ä¸ªé€‚é…å™¨ç±»å®ä¾‹ã€‚

ä¸ç®¡æ˜¯æ•è·å‹çš„è¿˜æ˜¯æœªæ•è·å‹çš„Lambdaè¡¨è¾¾å¼ï¼Œå®ƒä»¬çš„æ€§èƒ½ä¸Šé™çš†å¯ä»¥è¾¾åˆ°ç›´æ¥è°ƒç”¨çš„æ€§èƒ½ã€‚å…¶ä¸­ï¼Œæ•è·å‹Lambdaè¡¨è¾¾å¼å€ŸåŠ©äº†å³æ—¶ç¼–è¯‘å™¨ä¸­çš„é€ƒé€¸åˆ†æï¼Œæ¥é¿å…å®é™…çš„æ–°å»ºé€‚é…å™¨ç±»å®ä¾‹çš„æ“ä½œã€‚

åœ¨ä¸Šä¸€ç¯‡çš„è¯¾åå®è·µä¸­ï¼Œä½ åº”è¯¥æµ‹è¿‡è¿™ä¸€æ®µä»£ç çš„æ€§èƒ½å¼€é”€äº†ã€‚æˆ‘è¿™è¾¹æµ‹å¾—çš„ç»“æœçº¦ä¸ºç›´æ¥è°ƒç”¨çš„3.5å€ã€‚

```
// v8ç‰ˆæœ¬
import java.lang.invoke.MethodHandle;
import java.lang.invoke.MethodHandles;
import java.lang.invoke.MethodType;

public class Test {
  public static void target(int i) { }

  public static void main(String[] args) throws Exception {
    MethodHandles.Lookup l = MethodHandles.lookup();
    MethodType t = MethodType.methodType(void.class, int.class);
    MethodHandle mh = l.findStatic(Test.class, "target", t);

    long current = System.currentTimeMillis();
    for (int i = 1; i <= 2_000_000_000; i++) {
      if (i % 100_000_000 == 0) {
        long temp = System.currentTimeMillis();
        System.out.println(temp - current);
        current = temp;
      }

      mh.invokeExact(128);
    }
  }
}
```

å®é™…ä¸Šï¼Œå®ƒä¸ä½¿ç”¨Lambdaè¡¨è¾¾å¼æˆ–è€…æ–¹æ³•å¼•ç”¨çš„å·®åˆ«åœ¨äºï¼Œå³æ—¶ç¼–è¯‘å™¨æ— æ³•å°†è¯¥æ–¹æ³•å¥æŸ„è¯†åˆ«ä¸ºå¸¸é‡ï¼Œä»è€Œæ— æ³•è¿›è¡Œå†…è”ã€‚é‚£ä¹ˆå¦‚æœå°†å®ƒå˜æˆå¸¸é‡è¡Œä¸è¡Œå‘¢ï¼Ÿ

ä¸€ç§æ–¹æ³•ä¾¿æ˜¯å°†å…¶èµ‹å€¼ç»™finalçš„é™æ€å˜é‡ï¼Œå¦‚ä¸‹é¢çš„v9ç‰ˆæœ¬æ‰€ç¤ºï¼š

```
// v9ç‰ˆæœ¬
import java.lang.invoke.MethodHandle;
import java.lang.invoke.MethodHandles;
import java.lang.invoke.MethodType;

public class Test {
  public static void target(int i) { }

  static final MethodHandle mh;
  static {
    try {
      MethodHandles.Lookup l = MethodHandles.lookup();
      MethodType t = MethodType.methodType(void.class, int.class);
      mh = l.findStatic(Test.class, "target", t);
    } catch (Throwable e) {
      throw new RuntimeException(e);
    }
  }

  public static void main(String[] args) throws Throwable {
    long current = System.currentTimeMillis();
    for (int i = 1; i <= 2_000_000_000; i++) {
      if (i % 100_000_000 == 0) {
        long temp = System.currentTimeMillis();
        System.out.println(temp - current);
        current = temp;
      }

      mh.invokeExact(128);
    }
  }
}
```

è¿™ä¸ªç‰ˆæœ¬æµ‹å¾—çš„æ•°æ®å’Œç›´æ¥è°ƒç”¨çš„æ€§èƒ½æ•°æ®ä¸€è‡´ã€‚ä¹Ÿå°±æ˜¯è¯´ï¼Œå³æ—¶ç¼–è¯‘å™¨èƒ½å¤Ÿå°†è¯¥æ–¹æ³•å¥æŸ„å®Œå…¨å†…è”è¿›æ¥ï¼Œæˆä¸ºç©ºæ“ä½œã€‚

ä»Šå¤©çš„å®è·µç¯èŠ‚ï¼Œæˆ‘ä»¬æ¥ç»§ç»­æ¢ç´¢æ–¹æ³•å¥æŸ„çš„æ€§èƒ½ã€‚è¿è¡Œä¸‹é¢çš„v10ç‰ˆæœ¬ä»¥åŠv11ç‰ˆæœ¬ï¼Œæ¯”è¾ƒå®ƒä»¬çš„æ€§èƒ½å¹¶æ€è€ƒä¸ºä»€ä¹ˆã€‚

```
// v10ç‰ˆæœ¬
import java.lang.invoke.*;

public class Test {
  public static void target(int i) {
  }

  public static class MyCallSite {

    public final MethodHandle mh;

    public MyCallSite() {
      mh = findTarget();
    }

    private static MethodHandle findTarget() {
      try {
        MethodHandles.Lookup l = MethodHandles.lookup();
        MethodType t = MethodType.methodType(void.class, int.class);
        return l.findStatic(Test.class, "target", t);
      } catch (Throwable e) {
        throw new RuntimeException(e);
      }
    }
  }

  private static final MyCallSite myCallSite = new MyCallSite();

  public static void main(String[] args) throws Throwable {
    long current = System.currentTimeMillis();
    for (int i = 1; i <= 2_000_000_000; i++) {
      if (i % 100_000_000 == 0) {
        long temp = System.currentTimeMillis();
        System.out.println(temp - current);
        current = temp;
      }

      myCallSite.mh.invokeExact(128);
    }
  }
}

// v11ç‰ˆæœ¬
import java.lang.invoke.*;

public class Test {
  public static void target(int i) {
  }

  public static class MyCallSite extends ConstantCallSite {

    public MyCallSite() {
      super(findTarget());
    }

    private static MethodHandle findTarget() {
      try {
        MethodHandles.Lookup l = MethodHandles.lookup();
        MethodType t = MethodType.methodType(void.class, int.class);
        return l.findStatic(Test.class, "target", t);
      } catch (Throwable e) {
        throw new RuntimeException(e);
      }
    }
  }

  public static final MyCallSite myCallSite = new MyCallSite();

  public static void main(String[] args) throws Throwable {
    long current = System.currentTimeMillis();
    for (int i = 1; i <= 2_000_000_000; i++) {
      if (i % 100_000_000 == 0) {
        long temp = System.currentTimeMillis();
        System.out.println(temp - current);
        current = temp;
      }

      myCallSite.getTarget().invokeExact(128);
    }
  }
}
```

æ„Ÿè°¢ä½ çš„æ”¶å¬ï¼Œæˆ‘ä»¬ä¸‹æ¬¡å†è§ã€‚

\[1] [http://openjdk.java.net/jeps/303](http://openjdk.java.net/jeps/303)
<div><strong>ç²¾é€‰ç•™è¨€ï¼ˆ15ï¼‰</strong></div><ul>
<li><span>Shine</span> ğŸ‘ï¼ˆ27ï¼‰ ğŸ’¬ï¼ˆ1ï¼‰<p>ä¸€ç›´æ²¡ç†è§£â€œé€ƒé€¸åˆ†æâ€å•¥æ„æ€ï¼Ÿ</p>2018-08-14</li><br/><li><span>ã€€ç´ ä¸¶ã€€ã€€</span> ğŸ‘ï¼ˆ21ï¼‰ ğŸ’¬ï¼ˆ3ï¼‰<p>https:&#47;&#47;zhuanlan.zhihu.com&#47;p&#47;26389041
https:&#47;&#47;zhuanlan.zhihu.com&#47;p&#47;30936412
å¯ä»¥å’Œ Shijie å¤§å¤§çš„ä¸¤ç¯‡æ–‡ç« é…åˆç€çœ‹ã€‚</p>2018-11-07</li><br/><li><span>karl</span> ğŸ‘ï¼ˆ20ï¼‰ ğŸ’¬ï¼ˆ1ï¼‰<p>çœ‹äº†ä¸¤é å‹‰å¼ºæœ‰ä¸ªæ¦‚å¿µäº† 
è¿˜æ˜¯åŸºç¡€ä¸å¤Ÿ çœ‹ä¸æ‡‚å•Š</p>2018-08-14</li><br/><li><span>ext4</span> ğŸ‘ï¼ˆ17ï¼‰ ğŸ’¬ï¼ˆ1ï¼‰<p>æˆ‘çŸ¥é“Javaå¯¹Lambdaæœ‰ä¸ªè§„å®šï¼šâ€œThe variable used in Lambda should be final or effectively final&quot;ï¼Œä¹Ÿå°±æ˜¯è¯´Lambdaè¡¨è¾¾å¼æ•è·çš„å˜é‡å¿…é¡»æ˜¯finalæˆ–ç­‰åŒäºfinalçš„ã€‚è€Œæ–‡ä¸­æ‚¨åˆè®²åˆ°ï¼šâ€œå¯¹äºæ•è·äº†å˜é‡çš„Lambdaï¼Œæ¯æ¬¡invokedynamicéƒ½éœ€è¦æ–°å»ºé€‚é…å™¨ç±»å®ä¾‹ï¼Œä»¥é˜²æ­¢ä»–ä»¬å‘ç”Ÿå˜åŒ–â€ã€‚JVMä¹‹æ‰€ä»¥è¿™ä¹ˆåšï¼Œæ˜¯å› ä¸ºè¿™ç§finalçš„è¦æ±‚ä»…é™äºJava sourceå±‚é¢ï¼Œåœ¨bytecodeå±‚é¢æ˜¯æ˜¯æ— æ³•ä¿è¯çš„ã€‚æˆ‘ç†è§£çš„å¯¹å—ï¼Ÿ</p>2018-08-11</li><br/><li><span>Scott</span> ğŸ‘ï¼ˆ4ï¼‰ ğŸ’¬ï¼ˆ1ï¼‰<p>è€å¸ˆä½ å¥½ï¼Œæˆ‘æœ‰ä¸¤ä¸ªé—®é¢˜ï¼Œ1æ˜¯æˆ‘çœ‹äº†å‡ ä¸ªæœ‰invokedynmaicæŒ‡ä»¤çš„æ–‡ä»¶ï¼Œéƒ½æ˜¯invokedynamic #31,  0è¿™ç§å½¢å¼ï¼Œä¼¼ä¹åé¢è¿™ä¸ª0æ²¡æœ‰ä»€ä¹ˆä½œç”¨ï¼Œç½‘ä¸Šinvokedynamicçš„è§£è¯´ä¹Ÿå¤§å¤šè¿‡æ—¶ï¼Œæˆ‘ä½¿ç”¨çš„æ˜¯1.8.0_181ç‰ˆæœ¬ã€‚2. v10ç‰ˆæœ¬å’Œv11ç‰ˆæœ¬æ€§èƒ½çš„å·®è·æˆ‘çŒœæƒ³æ˜¯v10ç‰ˆæœ¬ä¸èƒ½æ­£ç¡®çš„å†…è”æ–¹æ³•å§ï¼Ÿè™½ç„¶mhæ˜¯finalçš„ï¼Œä½†æ˜¯å­—èŠ‚ç å±‚é¢å·²ç»ä¸¢å¤±è¿™ä¸ªä¿¡æ¯äº†ã€‚</p>2018-08-19</li><br/><li><span>å°æ©™æ©™</span> ğŸ‘ï¼ˆ2ï¼‰ ğŸ’¬ï¼ˆ1ï¼‰<p>å…¶å®æœ‰ä¸ªåœ°æ–¹ä¸€ç›´æ²¡æœ‰æƒ³é€ï¼Œä¸ºä»€ä¹ˆè¦å­¦ä¹ å­—èŠ‚ç ï¼Œå­¦ä¹ å­—èŠ‚ç å¯¹æˆ‘ä»¬æ—¥å¸¸å¼€å‘æœ‰ä»€ä¹ˆä½œç”¨å—ï¼Œè€å¸ˆèƒ½å¦ç»™æŒ‡ç‚¹è¿·æ´¥ä¸€ä¸‹ï¼Ÿ</p>2018-08-19</li><br/><li><span>Void_seT</span> ğŸ‘ï¼ˆ0ï¼‰ ğŸ’¬ï¼ˆ1ï¼‰<p>å•æ€å†…è”ç¼“å­˜çš„å®ç°ä»£ç æ®µï¼Œbootstrapæ–¹æ³•çš„å®ç°æœ‰é—®é¢˜ï¼Œæ²¡æœ‰returnä¸€ä¸ªCallSiteç±»å‹è¿”å›å€¼ã€‚å¦å¤–ï¼Œè¿™ç¯‡æœ‰ç‚¹éš¾åº¦äº†ï¼Œçœ‹äº†ä¸‰éï¼Œå‹‰å¼ºç†è§£ã€‚</p>2018-08-11</li><br/><li><span>lantern</span> ğŸ‘ï¼ˆ4ï¼‰ ğŸ’¬ï¼ˆ1ï¼‰<p>ç”¨invokedynamicå®ç°lambdaå‘ç”Ÿäº†ä»€ä¹ˆæ˜¯çœ‹æ‡‚äº†ï¼Œä½†æ²¡æœ‰å®Œå…¨æƒ³æ˜ç™½è¿™ä¹ˆåšçš„å¿…è¦æ€§ï¼Œè¿™æ ·åšç›¸æ¯”äºç¼–è¯‘æ—¶è§£lambdaè¯­æ³•ç³–ç”Ÿæˆä¸€ä¸ªåŒ¿åç±»æœ‰ä»€ä¹ˆå¥½å¤„å‘¢
æ˜¯å› ä¸ºå¯¹äºä¸æ•è·å±€éƒ¨å˜é‡çš„lambdaä¸ç”¨åå¤newå¯¹è±¡å—ï¼Œé‚£ä¹ˆå¯¹äºéœ€è¦æ•è·å±€éƒ¨å˜é‡çš„æƒ…å†µinvokedynamicçš„å®ç°æ–¹å¼è¿˜æœ‰ä»€ä¹ˆå…¶ä»–çš„å¥½å¤„å—</p>2020-08-16</li><br/><li><span>Kfreer</span> ğŸ‘ï¼ˆ4ï¼‰ ğŸ’¬ï¼ˆ1ï¼‰<p>å¦‚æœè¯¥ Lambda è¡¨è¾¾å¼æ•è·äº†å…¶ä»–å˜é‡ï¼Œé‚£ä¹ˆæ¯æ¬¡æ‰§è¡Œè¯¥ invokedynamic æŒ‡ä»¤ï¼Œæˆ‘ä»¬éƒ½è¦æ›´æ–°è¿™äº›æ•è·äº†çš„å˜åŒ–ã€‚
é—®é¢˜ï¼šæ•è·çš„å˜é‡å¿…é¡»æ˜¯finalï¼Œä¸ºä»€ä¹ˆè¿˜ä¼šå˜å‘¢ï¼Œä¸ºä»€ä¹ˆä¼šçº¿ç¨‹ä¸å®‰å…¨å‘¢ï¼Ÿ</p>2019-02-17</li><br/><li><span>çŒ´å“¥ä¸€ä¸€ cium</span> ğŸ‘ï¼ˆ3ï¼‰ ğŸ’¬ï¼ˆ0ï¼‰<p>çœ‹åˆ°å¤§å®¶éƒ½ä¸æ‡‚ï¼Œæˆ‘å°±æ”¾å¿ƒäº† ğŸ˜</p>2023-06-17</li><br/><li><span>å°é³„é±¼</span> ğŸ‘ï¼ˆ3ï¼‰ ğŸ’¬ï¼ˆ2ï¼‰<p>è€å¸ˆï¼Œçœ‹æ¥ä¸Šä¸€ç¯‡å’Œè¿™ç¯‡ï¼Œåˆä¸¤ä¸ªé—®é¢˜ï¼š
1. å°½ç®¡é€ƒé€¸åˆ†æèƒ½å¤Ÿå»é™¤è¿™äº›é¢å¤–çš„æ–°å»ºå®ä¾‹å¼€é”€ï¼Œä½†æ˜¯å®ƒä¹Ÿä¸æ˜¯æ—¶æ—¶å¥æ•ˆã€‚é‚£ä¹ˆä»€ä¹ˆæƒ…å†µä¸‹ä¸å¥æ•ˆå‘¢ï¼Ÿ
2. ä»€ä¹ˆæƒ…å†µä¸‹ç¼–è¯‘å™¨ä¼šå°†å¥æŸ„è¯†åˆ«æˆå¸¸é‡ï¼Ÿé™¤äº†æœ¬æ–‡ä¸­å°†MethodHandlerå®šä¹‰ä¸ºå¸¸é‡å¤–ï¼Œåœ¨å…¶ä»–ä»€ä¹ˆæƒ…å†µä¸‹èƒ½è¯†åˆ«ä¸ºå¸¸é‡å‘¢</p>2018-11-15</li><br/><li><span>snakorse</span> ğŸ‘ï¼ˆ2ï¼‰ ğŸ’¬ï¼ˆ0ï¼‰<p>è€å¸ˆï¼Œè¯·æ•™ä¸ªé—®é¢˜ï¼šjavaä¸ºä»€ä¹ˆé‡‡ç”¨åœ¨jvmä¸Šé€šè¿‡invokedynamicæ–¹å¼æ¥å®ç°lambdaï¼Œè€Œä¸ç›´æ¥é€šè¿‡åœ¨ç¼–è¯‘é˜¶æ®µç›´æ¥ç”Ÿæˆå’Œæ›¿æ¢ä»£ç çš„æ–¹å¼å®ç°ï¼Ÿ</p>2020-04-08</li><br/><li><span>ppyh</span> ğŸ‘ï¼ˆ1ï¼‰ ğŸ’¬ï¼ˆ0ï¼‰<p>æœ‰ä¸€ç‚¹ä¸å¤ªæ˜ç™½ï¼Œinvokeddynamicä¸ºä»€ä¹ˆè¦ç”¨methodHandleæ¥å®ç°ã€‚</p>2021-08-23</li><br/><li><span>zjiash</span> ğŸ‘ï¼ˆ0ï¼‰ ğŸ’¬ï¼ˆ0ï¼‰<p>V11å¯ä»¥è¾¾åˆ°å’Œç›´æ¥è°ƒç”¨è¿‘ä¼¼çš„æ‰§è¡Œæ•ˆç‡ï¼Œä½†æ˜¯V10ä¸å¯ä»¥ï¼Œåº”è¯¥æ˜¯æ–¹æ³•æ²¡æœ‰å†…è”ã€‚å¦å¤–ï¼ŒV9å¦‚æœä¸ä½¿ç”¨é™æ€å¸¸é‡ï¼Œè€Œæ˜¯åœ¨V8åŸºç¡€ä¸Šä½¿ç”¨å¸¸é‡ï¼Œå½¢å¦‚final MethodHandle mh = l.findStatic(Test.class, &quot;target&quot;, t); æ‰§è¡Œæ€§èƒ½ä¹Ÿä¼šæ¯”è¾ƒå·®ã€‚è¿™æ ·å’ŒV10ç±»ä¼¼ï¼Œä¸çŸ¥é“ä¸ºä»€ä¹ˆè¿™2ç§æƒ…å†µæ²¡æœ‰è¿›è¡Œå†…è”ï¼Ÿ</p>2023-10-27</li><br/><li><span>Geek_a7016f</span> ğŸ‘ï¼ˆ0ï¼‰ ğŸ’¬ï¼ˆ0ï¼‰<p>è€å¸ˆèƒ½æä¾›ä¸€äº›å‰ç½®åŸºç¡€èµ„æ–™å—ï¼Ÿæ–‡ç« æ„Ÿè§‰æœ‰ç‚¹éš¾åº¦ã€‚</p>2022-08-31</li><br/>
</ul>